regula/__init__.py
regula/facerecognition/__init__.py
regula/facerecognition/webclient/__init__.py
regula/facerecognition/webclient/ext/__init__.py
regula/facerecognition/webclient/ext/common.py
regula/facerecognition/webclient/ext/api/__init__.py
regula/facerecognition/webclient/ext/api/matching_api.py
regula/facerecognition/webclient/ext/api/sdk.py
regula/facerecognition/webclient/ext/models/__init__.py
regula/facerecognition/webclient/ext/models/compare_image.py
regula/facerecognition/webclient/ext/models/compare_request.py
regula/facerecognition/webclient/ext/models/detect_request.py
regula/facerecognition/webclient/gen/__init__.py
regula/facerecognition/webclient/gen/api_client.py
regula/facerecognition/webclient/gen/configuration.py
regula/facerecognition/webclient/gen/exceptions.py
regula/facerecognition/webclient/gen/rest.py
regula/facerecognition/webclient/gen/api/__init__.py
regula/facerecognition/webclient/gen/api/matching_api.py
regula/facerecognition/webclient/gen/models/__init__.py
regula/facerecognition/webclient/gen/models/compare_image.py
regula/facerecognition/webclient/gen/models/compare_image_detection.py
regula/facerecognition/webclient/gen/models/compare_image_result.py
regula/facerecognition/webclient/gen/models/compare_request.py
regula/facerecognition/webclient/gen/models/compare_response.py
regula/facerecognition/webclient/gen/models/compare_response_all_of.py
regula/facerecognition/webclient/gen/models/detect_request.py
regula/facerecognition/webclient/gen/models/detect_response.py
regula/facerecognition/webclient/gen/models/detect_response_all_of.py
regula/facerecognition/webclient/gen/models/detect_result.py
regula/facerecognition/webclient/gen/models/detection.py
regula/facerecognition/webclient/gen/models/detection_face.py
regula/facerecognition/webclient/gen/models/face_recognition_result.py
regula/facerecognition/webclient/gen/models/face_recognition_result_code.py
regula/facerecognition/webclient/gen/models/image_source.py
regula.facerecognition.webclient-2.1.0.dist-info/METADATA
regula.facerecognition.webclient-2.1.0.dist-info/WHEEL
regula.facerecognition.webclient-2.1.0.dist-info/top_level.txt
regula.facerecognition.webclient-2.1.0.dist-info/RECORD
