Metadata-Version: 2.1
Name: regula.facerecognition.webclient
Version: 2.1.0
Summary: Regula's Face Recognition python client
Home-page: https://mobile.regulaforensics.com
Author: Regula Forensics, Inc.
Author-email: support@regulaforensics.com
License: UNKNOWN
Keywords: face-recognition-client,face recognition,facer,regulaforensics,regula
Platform: UNKNOWN
Requires-Python: >=3.5
